wecover/__init__.py
wecover/image.py
wecover-0.2.0.dist-info/LICENSE
wecover-0.2.0.dist-info/METADATA
wecover-0.2.0.dist-info/WHEEL
wecover-0.2.0.dist-info/entry_points.txt
wecover-0.2.0.dist-info/top_level.txt
wecover-0.2.0.dist-info/RECORD
