Metadata-Version: 2.1
Name: wecover
Version: 0.2.0
Summary: 微信公众号图文封面快速制作工具。
Home-page: https://github.com/kenblikylee/wecover
Author: ken
Author-email: kenbliky@gmail.com
License: MIT
Platform: UNKNOWN
Classifier: Programming Language :: Python :: 3
Classifier: License :: OSI Approved :: MIT License
Classifier: Operating System :: OS Independent
Requires-Python: >=3.6
Requires-Dist: requests (>=2.21.0)
Requires-Dist: Pillow (>=6.1.0)
